.coveragerc
.editorconfig
.gitignore
.travis.yml
LICENSE
README.md
pyproject.toml
requirements.txt
requirements_dev.txt
setup.cfg
setup.py
.github/workflows/python-publish.yml
democritus_fun/__init__.py
democritus_fun/fun.py
democritus_fun/fun_temp_utils.py
democritus_fun.egg-info/PKG-INFO
democritus_fun.egg-info/SOURCES.txt
democritus_fun.egg-info/dependency_links.txt
democritus_fun.egg-info/requires.txt
democritus_fun.egg-info/top_level.txt
democritus_fun.egg-info/zip-safe
tests/__init__.py
tests/test_fun.py