Metadata-Version: 2.1
Name: democritus-fun
Version: 2021.1.25
Summary: Fun Democritus functions.
Home-page: https://github.com/democritus-project/democritus-fun
Author: Floyd Hightower
Author-email: floyd.hightower27@gmail.com
License: MIT license
Keywords: democritus,utility,python,fun-things,fun-things-utility,fun,joy,easter-eggs
Platform: UNKNOWN
Classifier: Development Status :: 2 - Pre-Alpha
Classifier: Intended Audience :: Developers
Classifier: License :: OSI Approved :: MIT License
Classifier: Natural Language :: English
Classifier: Programming Language :: Python :: 3
Classifier: Programming Language :: Python :: 3.4
Classifier: Programming Language :: Python :: 3.5
Classifier: Programming Language :: Python :: 3.6
Classifier: Programming Language :: Python :: 3.7
Classifier: Programming Language :: Python :: 3.8
Classifier: Programming Language :: Python :: 3.9
